MANIFEST.in
README.md
setup.py
filter_profanity.egg-info/PKG-INFO
filter_profanity.egg-info/SOURCES.txt
filter_profanity.egg-info/dependency_links.txt
filter_profanity.egg-info/top_level.txt
profanity/__init__.py
profanity/config.py
profanity/util.py
profanity/data/profanity.json