Metadata-Version: 2.1
Name: filter-profanity
Version: 1.0.8
Summary: The fastest python module to filter and censor obscene language from strings!
Home-page: https://github.com/TrustedMercury/filter-profanity
Author: TrustedMercury
Author-email: trustedmercury@gmail.com
License: UNKNOWN
Keywords: profanity,filter,censor
Platform: UNKNOWN
Classifier: Programming Language :: Python :: 3
Classifier: License :: OSI Approved :: MIT License
Classifier: Operating System :: OS Independent
Requires-Python: >=3.6
